README
perlinpinpin.py
setup.py
perlinpinpin.egg-info/PKG-INFO
perlinpinpin.egg-info/SOURCES.txt
perlinpinpin.egg-info/dependency_links.txt
perlinpinpin.egg-info/top_level.txt
