Metadata-Version: 1.0
Name: perlinpinpin
Version: 0.6
Summary: Convert french fuzzy date to a python date object.
Home-page: UNKNOWN
Author: Timothee Peignier
Author-email: tim@tryphon.org
License: MIT License
Keywords: convert fuzzy date time french
Platform: UNKNOWN
Classifier: Development Status :: 4 - Beta
Classifier: License :: OSI Approved :: MIT License
Classifier: Operating System :: OS Independent
Classifier: Programming Language :: Python
Classifier: Topic :: Software Development :: Libraries :: Python Modules
